dbtoolspy/__init__.py
dbtoolspy/column.py
dbtoolspy/connection.py
dbtoolspy/database.py
dbtoolspy/table.py
dbtoolspy-0.0.2.dist-info/LICENSE.txt
dbtoolspy-0.0.2.dist-info/METADATA
dbtoolspy-0.0.2.dist-info/WHEEL
dbtoolspy-0.0.2.dist-info/top_level.txt
dbtoolspy-0.0.2.dist-info/RECORD
